{
    "name": "trophy_retrieval_example",
    "version": 2,
    "ceilingMaterial": "AI2-THOR/Materials/Walls/Drywall",
    "floorMaterial": "AI2-THOR/Materials/Fabrics/CarpetWhite 3",
    "wallMaterial": "AI2-THOR/Materials/Walls/DrywallBeige",
    "performerStart": {
        "position": {
            "x": 0,
            "z": 0
        },
        "rotation": {
            "x": 0,
            "y": 0
        }
    },
    "objects": [{
        "id": "trophy",
        "type": "trophy",
        "shows": [{
            "stepBegin": 0,
            "position": {
                "x": 0,
                "y": 0,
                "z": 2
            }
        }]
    }],
    "goal": {
        "category": "retrieval",
        "description": "Find and pick up the trophy.",
        "last_step": 3000,
        "metadata": {
            "target": {
                "id": "trophy",
                "image": null
            }
        }
    }
}
