{
  "doors": [
    {
      "assetId": "Doorway_6",
      "assetOffset": {
        "x": -0.0009746691212058067,
        "y": -0.0,
        "z": 0.03902848809957504
      },
      "boundingBox": {
        "max": {
          "x": 2.322157177045987,
          "y": 2.1068506240844727,
          "z": 0
        },
        "min": {
          "x": 1.2845788327008942,
          "y": 0,
          "z": 0
        }
      },
      "id": "door|4|5",
      "openable": true,
      "openness": 1,
      "room0": "room|5",
      "room1": "room|4",
      "wall0": "wall|5|6.51|0.00|6.51|6.51",
      "wall1": "wall|4|6.51|0.00|6.51|6.51"
    },
    {
      "assetId": "Doorframe_Double_9",
      "assetOffset": {
        "x": 2.6067718863487244e-06,
        "y": -0.0,
        "z": 0.0655703991651535
      },
      "boundingBox": {
        "max": {
          "x": 6.095970777179931,
          "y": 2.075340747833252,
          "z": 0
        },
        "min": {
          "x": 4.185718563701843,
          "y": 0,
          "z": 0
        }
      },
      "id": "door|6|7",
      "room0": "room|7",
      "room1": "room|6",
      "wall0": "wall|7|8.68|6.51|8.68|13.02",
      "wall1": "wall|6|8.68|6.51|8.68|13.02"
    },
    {
      "assetId": "Doorway_6",
      "assetOffset": {
        "x": -0.0009746691212058067,
        "y": -0.0,
        "z": 0.03902848809957504
      },
      "boundingBox": {
        "max": {
          "x": 2.0064745639758677,
          "y": 2.1068506240844727,
          "z": 0
        },
        "min": {
          "x": 0.9688962196307747,
          "y": 0,
          "z": 0
        }
      },
      "id": "door|4|6",
      "openable": true,
      "openness": 1,
      "room0": "room|4",
      "room1": "room|6",
      "wall0": "wall|4|6.51|6.51|8.68|6.51",
      "wall1": "wall|6|6.51|6.51|8.68|6.51"
    },
    {
      "assetId": "Doorway_Double_2",
      "assetOffset": {
        "x": -0.0013517113402485847,
        "y": -0.0,
        "z": 0.07298704236745834
      },
      "boundingBox": {
        "max": {
          "x": 2.236006342646875,
          "y": 2.0728204250335693,
          "z": 0
        },
        "min": {
          "x": 0.32248326468209243,
          "y": 0,
          "z": 0
        }
      },
      "id": "door|1|6",
      "openable": false,
      "openness": 0,
      "room0": "room|6",
      "room1": "room|6",
      "wall0": "wall|6|0.00|6.51|0.00|13.02",
      "wall1": "wall|exterior|0.00|6.51|0.00|13.02"
    }
  ],
  "metadata": {
    "agent": {
      "horizon": 30,
      "position": {
        "x": 5.25,
        "y": 0.95,
        "z": 3.5
      },
      "rotation": {
        "x": 0,
        "y": 180,
        "z": 0
      },
      "standing": true
    },
    "roomSpecId": "4-room",
    "schema": "0.0.1",
    "warnings": {}
  },
  "objects": [
    {
      "assetId": "Bed_20",
      "children": [
        {
          "assetId": "pillow_3",
          "id": "4|0|2",
          "kinematic": false,
          "position": {
            "x": 12.54885456097126,
            "y": 0.7418022826313972,
            "z": 0.903635528683663
          },
          "rotation": {
            "x": 0,
            "y": 270.0,
            "z": 0
          },
          "layer": "Procedural3"
        },
        {
          "assetId": "pillow_3",
          "id": "4|0|1",
          "kinematic": false,
          "position": {
            "x": 12.54885456097126,
            "y": 0.7418022826313972,
            "z": 0.3106206864118586
          },
          "rotation": {
            "x": 0,
            "y": 270.0,
            "z": 0
          },
          "layer": "Procedural3"
        },
        {
          "assetId": "BaseballBat_4",
          "id": "small|4|2",
          "kinematic": false,
          "position": {
            "x": 12.336759567260742,
            "y": 0.9721850156784058,
            "z": 0.2740974426269531
          },
          "rotation": {
            "x": 18.692420959472656,
            "y": 210.60757446289062,
            "z": 25.274513244628906
          },
          "layer": "Procedural3"
        },
        {
          "assetId": "Cellphone_7",
          "id": "small|4|5",
          "kinematic": false,
          "position": {
            "x": 11.504834175109863,
            "y": 0.5919232845306397,
            "z": 0.7480465769767761
          },
          "rotation": {
            "x": -0.0,
            "y": 0.0,
            "z": 0.0
          },
          "layer": "Procedural3"
        }
      ],
      "id": "4|0|0",
      "isDirty": true,
      "kinematic": true,
      "position": {
        "x": 11.982498304367065,
        "y": 0.33712294697761536,
        "z": 0.6071281075477607
      },
      "rotation": {
        "x": 0,
        "y": 270.0,
        "z": 0
      },
      "layer": "Procedural3"
    },
    {
      "assetId": "Dresser_224_1",
      "children": [
        {
          "assetId": "Desk_Lamp_2",
          "id": "small|4|1",
          "isOn": true,
          "kinematic": false,
          "position": {
            "x": 12.451231002807617,
            "y": 1.0995227098464966,
            "z": 2.7840800285339355
          },
          "rotation": {
            "x": 0.0,
            "y": -2.390565896348562e-05,
            "z": 0.0
          },
          "layer": "Procedural3"
        },
        {
          "assetId": "Book_3",
          "id": "small|4|6",
          "kinematic": false,
          "position": {
            "x": 12.450512886047363,
            "y": 0.912715494632721,
            "z": 3.7372355461120605
          },
          "rotation": {
            "x": 0.0,
            "y": -2.390565896348562e-05,
            "z": 0.0
          },
          "layer": "Procedural3"
        },
        {
          "assetId": "Houseplant_2",
          "id": "small|4|7",
          "kinematic": false,
          "position": {
            "x": 12.687978744506836,
            "y": 1.2475190162658691,
            "z": 3.737687110900879
          },
          "rotation": {
            "x": 0.0,
            "y": -2.390565896348562e-05,
            "z": 0.0
          },
          "layer": "Procedural3"
        }
      ],
      "id": "4|1",
      "kinematic": true,
      "position": {
        "x": 12.631648139476775,
        "y": 0.4467717111110687,
        "z": 3.023201571490533
      },
      "rotation": {
        "x": 0,
        "y": 270,
        "z": 0
      },
      "layer": "Procedural3"
    },
    {
      "assetId": "Dining_Table_208_1",
      "children": [
        {
          "assetId": "Bowl_23",
          "id": "small|4|0",
          "kinematic": false,
          "position": {
            "x": 8.908828735351562,
            "y": 0.8806946754455567,
            "z": 4.672821998596191
          },
          "rotation": {
            "x": -0.0,
            "y": 0.0,
            "z": 0.0
          },
          "layer": "Procedural3"
        },
        {
          "assetId": "Mug_1",
          "id": "small|4|3",
          "kinematic": false,
          "position": {
            "x": 9.563376426696777,
            "y": 0.8842073559761048,
            "z": 4.79640007019043
          },
          "rotation": {
            "x": -0.0,
            "y": 0.0,
            "z": 0.0
          },
          "layer": "Procedural3"
        },
        {
          "assetId": "Vase_Medium_3",
          "id": "small|4|8",
          "kinematic": false,
          "position": {
            "x": 10.018755912780762,
            "y": 0.9301507353782654,
            "z": 4.796550273895264
          },
          "rotation": {
            "x": -0.0,
            "y": 0.0,
            "z": 0.0
          },
          "layer": "Procedural3"
        }
      ],
      "id": "4|2|0",
      "kinematic": true,
      "position": {
        "x": 9.352993136125594,
        "y": 0.39023110270500183,
        "z": 5.043749944607917
      },
      "rotation": {
        "x": 0,
        "y": 0.0,
        "z": 0
      },
      "layer": "Procedural3"
    },
    {
      "assetId": "Chair_205_1",
      "id": "4|2|1",
      "kinematic": true,
      "position": {
        "x": 10.402554252820998,
        "y": 0.4374691843986511,
        "z": 5.043749944607917
      },
      "rotation": {
        "x": 0,
        "y": 259.2180068835601,
        "z": 0
      },
      "layer": "Procedural3"
    },
    {
      "assetId": "Chair_205_1",
      "id": "4|2|2",
      "kinematic": true,
      "position": {
        "x": 8.30343201943019,
        "y": 0.4374691843986511,
        "z": 5.043749944607917
      },
      "rotation": {
        "x": 0,
        "y": 75.67740160919541,
        "z": 0
      },
      "layer": "Procedural3"
    },
    {
      "assetId": "Chair_205_1",
      "id": "4|2|3",
      "kinematic": true,
      "position": {
        "x": 8.885778552244219,
        "y": 0.4374691843986511,
        "z": 4.449898521344367
      },
      "rotation": {
        "x": 0,
        "y": 348.0684923160037,
        "z": 0
      },
      "layer": "Procedural3"
    },
    {
      "assetId": "Chair_205_1",
      "id": "4|2|4",
      "kinematic": true,
      "position": {
        "x": 8.853145937732341,
        "y": 0.4374691843986511,
        "z": 5.637601367871467
      },
      "rotation": {
        "x": 0,
        "y": 177.18535972485202,
        "z": 0
      },
      "layer": "Procedural3"
    },
    {
      "assetId": "Chair_205_1",
      "id": "4|2|5",
      "kinematic": true,
      "position": {
        "x": 9.80734804976117,
        "y": 0.4374691843986511,
        "z": 5.637601367871467
      },
      "rotation": {
        "x": 0,
        "y": 163.89341868111498,
        "z": 0
      },
      "layer": "Procedural3"
    },
    {
      "assetId": "Chair_205_1",
      "id": "4|2|6",
      "kinematic": true,
      "position": {
        "x": 9.79532780581595,
        "y": 0.4374691843986511,
        "z": 4.449898521344367
      },
      "rotation": {
        "x": 0,
        "y": 20.503589019972146,
        "z": 0
      },
      "layer": "Procedural3"
    },
    {
      "assetId": "Armchair_201_3",
      "id": "4|3|0",
      "kinematic": true,
      "position": {
        "x": 7.7567518496793255,
        "y": 0.3458659052848816,
        "z": 0.39213561415672304
      },
      "rotation": {
        "x": 0,
        "y": 0.0,
        "z": 0
      },
      "layer": "Procedural3"
    },
    {
      "assetId": "Floor_Lamp_2",
      "id": "4|3|1",
      "isOn": true,
      "kinematic": false,
      "position": {
        "x": 6.862373942985224,
        "y": 1.038681983947754,
        "z": 0.39213561415672304
      },
      "rotation": {
        "x": 0,
        "y": 291.6439284430453,
        "z": 0
      },
      "layer": "Procedural3"
    },
    {
      "assetId": "Desk_326_1",
      "children": [
        {
          "assetId": "Laptop_26",
          "id": "small|4|4",
          "kinematic": false,
          "openness": 1,
          "position": {
            "x": 6.770424842834473,
            "y": 1.021066415309906,
            "z": 1.900618553161621
          },
          "rotation": {
            "x": -0.0,
            "y": 179.99998474121094,
            "z": -0.0
          },
          "layer": "Procedural3"
        },
        {
          "assetId": "CD_1",
          "id": "small|4|9",
          "kinematic": false,
          "position": {
            "x": 6.594699859619141,
            "y": 0.7979850769042969,
            "z": 2.452877998352051
          },
          "rotation": {
            "x": -0.0,
            "y": 179.99998474121094,
            "z": -0.0
          },
          "layer": "Procedural3"
        }
      ],
      "id": "4|4",
      "kinematic": true,
      "position": {
        "x": 6.779584564447402,
        "y": 0.3957439064979553,
        "z": 2.4510973620054255
      },
      "rotation": {
        "x": 0,
        "y": 90,
        "z": 0
      },
      "layer": "Procedural3"
    },
    {
      "assetId": "RoboTHOR_basketball_rhode_island_novelty_v",
      "id": "4|5",
      "kinematic": false,
      "position": {
        "x": 10.118629966002434,
        "y": 0.1203056275844574,
        "z": 2.5595660285271706
      },
      "rotation": {
        "x": 0,
        "y": 0,
        "z": 0
      },
      "layer": "Procedural3"
    },
    {
      "assetId": "Toilet_2",
      "children": [
        {
          "assetId": "Spray_Bottle_4",
          "id": "small|5|11",
          "kinematic": false,
          "position": {
            "x": 0.07917558401823044,
            "y": 1.0737868547439575,
            "z": 4.758962154388428
          },
          "rotation": {
            "x": -0.0,
            "y": 179.99984741210938,
            "z": -0.0
          },
          "layer": "Procedural1"
        }
      ],
      "id": "5|0",
      "kinematic": true,
      "position": {
        "x": 0.4562047362327576,
        "y": 0.472759485244751,
        "z": 4.633853025674821
      },
      "rotation": {
        "x": 0,
        "y": 90,
        "z": 0
      },
      "layer": "Procedural1"
    },
    {
      "assetId": "Sink_19",
      "children": [
        {
          "assetId": "Bathroom_Faucet_2",
          "id": "5|1|1",
          "kinematic": true,
          "position": {
            "x": 4.723495997428895,
            "y": 1.1451617404818535,
            "z": 0.15869933247566215
          },
          "rotation": {
            "x": 0,
            "y": 0.0,
            "z": 0
          },
          "layer": "Procedural1"
        },
        {
          "assetId": "Soap_Bottle_14",
          "id": "small|5|10",
          "kinematic": false,
          "position": {
            "x": 4.643176078796387,
            "y": 0.9666251540184021,
            "z": 0.47855937480926514
          },
          "rotation": {
            "x": 1.403341910044412e-14,
            "y": -0.0,
            "z": -0.0
          },
          "layer": "Procedural1"
        }
      ],
      "id": "5|1|0",
      "kinematic": true,
      "position": {
        "x": 4.723495997428895,
        "y": 0.5229595303535461,
        "z": 0.38788666725158694
      },
      "rotation": {
        "x": 0,
        "y": 0.0,
        "z": 0
      },
      "layer": "Procedural1"
    },
    {
      "assetId": "Dresser_229_1",
      "id": "5|2",
      "kinematic": true,
      "position": {
        "x": 4.626938195350987,
        "y": 0.35076457262039185,
        "z": 6.284331013441086
      },
      "rotation": {
        "x": 0,
        "y": 180,
        "z": 0
      },
      "layer": "Procedural1"
    },
    {
      "assetId": "Countertop_C_10x6",
      "children": [
        {
          "assetId": "Soap_Bottle_11",
          "id": "small|6|12",
          "kinematic": false,
          "position": {
            "x": 0.32976657152175903,
            "y": 1.0384641885757446,
            "z": 11.292709350585938
          },
          "rotation": {
            "x": 0.0,
            "y": 180.0,
            "z": 0.0
          },
          "layer": "Procedural2"
        },
        {
          "assetId": "Microwave_26",
          "id": "small|6|13",
          "kinematic": false,
          "position": {
            "x": 2.3105921745300293,
            "y": 1.1407833099365234,
            "z": 12.768773078918457
          },
          "rotation": {
            "x": 0.0,
            "y": 180.0,
            "z": 0.0
          },
          "layer": "Procedural2"
        },
        {
          "assetId": "Dish_Sponge_1",
          "id": "small|6|14",
          "kinematic": false,
          "position": {
            "x": 0.40381547808647156,
            "y": 0.9551413059234619,
            "z": 12.610732078552246
          },
          "rotation": {
            "x": 0.0,
            "y": 180.0,
            "z": 0.0
          },
          "layer": "Procedural2"
        },
        {
          "assetId": "Ladle_1",
          "id": "small|6|15",
          "kinematic": false,
          "position": {
            "x": 0.40799057483673096,
            "y": 0.9674525260925293,
            "z": 11.280374526977539
          },
          "rotation": {
            "x": 0.0,
            "y": 180.0,
            "z": 0.0
          },
          "layer": "Procedural2"
        },
        {
          "assetId": "coffee_machine_29",
          "id": "small|6|18",
          "kinematic": false,
          "position": {
            "x": 2.688431739807129,
            "y": 1.1689116954803467,
            "z": 11.390300750732422
          },
          "rotation": {
            "x": 0.0,
            "y": 180.0,
            "z": 0.0
          },
          "layer": "Procedural2"
        },
        {
          "assetId": "Cup_23",
          "id": "small|6|19",
          "kinematic": false,
          "position": {
            "x": 2.9969165325164795,
            "y": 1.0583962678909302,
            "z": 11.293584823608398
          },
          "rotation": {
            "x": 0.0,
            "y": 180.0,
            "z": 0.0
          },
          "layer": "Procedural2"
        },
        {
          "assetId": "Mug_1",
          "id": "small|6|20",
          "kinematic": false,
          "position": {
            "x": 0.7966302633285522,
            "y": 1.0441383004188538,
            "z": 12.687995910644531
          },
          "rotation": {
            "x": 0.0,
            "y": 180.0,
            "z": 0.0
          },
          "layer": "Procedural2"
        },
        {
          "assetId": "Kettle_1",
          "id": "small|6|22",
          "kinematic": false,
          "position": {
            "x": 1.1663711071014404,
            "y": 1.035681962966919,
            "z": 12.684833526611328
          },
          "rotation": {
            "x": 0.0,
            "y": 180.0,
            "z": 0.0
          },
          "layer": "Procedural2"
        }
      ],
      "id": "6|0",
      "kinematic": true,
      "position": {
        "x": 1.5490001678466796,
        "y": 0.46919137239456177,
        "z": 12.065393702507018
      },
      "rotation": {
        "x": 0,
        "y": 180,
        "z": 0
      },
      "layer": "Procedural2"
    },
    {
      "assetId": "RoboTHOR_dining_table_extendable",
      "children": [
        {
          "assetId": "Bowl_10",
          "id": "small|6|21",
          "kinematic": false,
          "position": {
            "x": 5.09050178527832,
            "y": 0.7885723114013672,
            "z": 8.91770076751709
          },
          "rotation": {
            "x": 0.0,
            "y": 270.0,
            "z": 0.0
          },
          "layer": "Procedural2"
        }
      ],
      "id": "6|1|0",
      "kinematic": true,
      "position": {
        "x": 5.207656292592143,
        "y": 0.3721551299095154,
        "z": 8.91884631312481
      },
      "rotation": {
        "x": 0,
        "y": 270.0,
        "z": 0
      },
      "layer": "Procedural2"
    },
    {
      "assetId": "Chair_215_2",
      "id": "6|1|1",
      "kinematic": true,
      "position": {
        "x": 4.644564442311381,
        "y": 0.5340867042541504,
        "z": 8.91884631312481
      },
      "rotation": {
        "x": 0,
        "y": 108.58726474976521,
        "z": 0
      },
      "layer": "Procedural2"
    },
    {
      "assetId": "Chair_215_2",
      "id": "6|1|2",
      "kinematic": true,
      "position": {
        "x": 5.770748142872905,
        "y": 0.5340867042541504,
        "z": 8.91884631312481
      },
      "rotation": {
        "x": 0,
        "y": 284.14358210823355,
        "z": 0
      },
      "layer": "Procedural2"
    },
    {
      "assetId": "Fridge_23",
      "children": [
        {
          "assetId": "Egg_19",
          "id": "small|6|16",
          "kinematic": false,
          "position": {
            "x": 4.707371711730957,
            "y": 1.1919533491134644,
            "z": 12.554500579833984
          },
          "rotation": {
            "x": 0.0,
            "y": 180.0,
            "z": 0.0
          },
          "layer": "Procedural2"
        },
        {
          "assetId": "Egg_9",
          "id": "small|6|17",
          "kinematic": false,
          "position": {
            "x": 4.498145580291748,
            "y": 1.4862105131149292,
            "z": 12.652325630187988
          },
          "rotation": {
            "x": 0.0,
            "y": 180.0,
            "z": 0.0
          },
          "layer": "Procedural2"
        }
      ],
      "id": "6|2",
      "kinematic": true,
      "position": {
        "x": 4.498145382477736,
        "y": 1.0191432237625122,
        "z": 12.61741627883911
      },
      "rotation": {
        "x": 0,
        "y": 180,
        "z": 0
      },
      "layer": "Procedural2"
    },
    {
      "assetId": "Houseplant_27",
      "id": "6|3|0",
      "kinematic": false,
      "position": {
        "x": 1.9302349595471417,
        "y": 0.44784826040267944,
        "z": 6.66910778575428
      },
      "rotation": {
        "x": 0,
        "y": 355.50283579241227,
        "z": 0
      },
      "layer": "Procedural2"
    },
    {
      "assetId": "TV_Stand_206_3",
      "children": [
        {
          "assetId": "Television_3",
          "id": "7|0|1",
          "kinematic": true,
          "position": {
            "x": 12.690244005441665,
            "y": 1.1425487399101257,
            "z": 12.346352593421935
          },
          "rotation": {
            "x": 0,
            "y": 270.0,
            "z": 0
          },
          "layer": "Procedural1"
        }
      ],
      "id": "7|0|0",
      "kinematic": true,
      "position": {
        "x": 12.690244005441665,
        "y": 0.37625908851623535,
        "z": 12.346352593421935
      },
      "rotation": {
        "x": 0,
        "y": 270.0,
        "z": 0
      },
      "layer": "Procedural1"
    },
    {
      "assetId": "Dining_Table_21_3",
      "children": [
        {
          "assetId": "Book_28",
          "id": "small|7|23",
          "kinematic": false,
          "position": {
            "x": 12.36395263671875,
            "y": 0.8808724880218506,
            "z": 7.056154251098633
          },
          "rotation": {
            "x": -0.0,
            "y": -8.196226553991437e-05,
            "z": 0.0
          },
          "layer": "Procedural1"
        }
      ],
      "id": "7|1",
      "kinematic": true,
      "position": {
        "x": 12.575819061517715,
        "y": 0.4304693937301636,
        "z": 7.058870323181152
      },
      "rotation": {
        "x": 0,
        "y": 270,
        "z": 0
      },
      "layer": "Procedural1"
    },
    {
      "assetId": "Sofa_201_1",
      "id": "7|2",
      "kinematic": true,
      "position": {
        "x": 10.335840894911867,
        "y": 0.5753807425498962,
        "z": 7.021842606544494
      },
      "rotation": {
        "x": 0,
        "y": 0,
        "z": 0
      },
      "layer": "Procedural1"
    },
    {
      "assetId": "Armchair_227_1",
      "id": "7|3|0",
      "kinematic": true,
      "position": {
        "x": 12.582482741594314,
        "y": 0.30783283710479736,
        "z": 10.602606721478843
      },
      "rotation": {
        "x": 0,
        "y": 270.0,
        "z": 0
      },
      "layer": "Procedural1"
    },
    {
      "assetId": "Floor_Lamp_3",
      "id": "7|3|1",
      "isOn": true,
      "kinematic": false,
      "position": {
        "x": 12.582482741594314,
        "y": 0.9515953063964844,
        "z": 9.582922400693608
      },
      "rotation": {
        "x": 0,
        "y": 333.3965121787431,
        "z": 0
      },
      "layer": "Procedural1"
    },
    {
      "assetId": "RoboTHOR_armchair_overallt",
      "id": "7|4|0",
      "kinematic": true,
      "position": {
        "x": 10.576190803895237,
        "y": 0.31184715032577515,
        "z": 12.601737965560826
      },
      "rotation": {
        "x": 0,
        "y": 180.0,
        "z": 0
      },
      "layer": "Procedural1"
    },
    {
      "assetId": "Floor_Lamp_10",
      "id": "7|4|1",
      "isOn": false,
      "kinematic": false,
      "position": {
        "x": 9.718950997789229,
        "y": 0.9447612166404724,
        "z": 12.601737965560826
      },
      "rotation": {
        "x": 0,
        "y": 335.2367427632049,
        "z": 0
      },
      "layer": "Procedural1"
    },
    {
      "assetId": "Wall_Decor_Painting_6",
      "id": "5|3",
      "kinematic": true,
      "position": {
        "x": 5.397390013450162,
        "y": 1.9293552924759831,
        "z": 6.48665
      },
      "rotation": {
        "x": 0,
        "y": 180,
        "z": 0
      },
      "layer": "Procedural1"
    },
    {
      "assetId": "Wall_Decor_Photo_1V",
      "id": "5|4",
      "kinematic": true,
      "position": {
        "x": 6.487129514545202,
        "y": 1.4683671011001098,
        "z": 3.852052743497921
      },
      "rotation": {
        "x": 0,
        "y": 270,
        "z": 0
      },
      "layer": "Procedural1"
    },
    {
      "assetId": "Wall_Decor_Painting_10",
      "id": "6|4",
      "kinematic": true,
      "position": {
        "x": 1.4059414229496607,
        "y": 1.6635244660261113,
        "z": 6.520999651134014
      },
      "rotation": {
        "x": 0,
        "y": 0,
        "z": 0
      },
      "layer": "Procedural2"
    },
    {
      "assetId": "Wall_Decor_Photo_2",
      "id": "6|5",
      "kinematic": true,
      "position": {
        "x": 5.504321809440211,
        "y": 1.428475762103659,
        "z": 12.996129514545201
      },
      "rotation": {
        "x": 0,
        "y": 180,
        "z": 0
      },
      "layer": "Procedural2"
    },
    {
      "assetId": "Wall_Decor_Photo_6",
      "id": "4|6",
      "kinematic": true,
      "position": {
        "x": 12.996129514545201,
        "y": 1.15535767874667,
        "z": 4.996343194907494
      },
      "rotation": {
        "x": 0,
        "y": 270,
        "z": 0
      },
      "layer": "Procedural3"
    },
    {
      "assetId": "Wall_Decor_Painting_9",
      "id": "7|5",
      "kinematic": true,
      "position": {
        "x": 13.002425275638698,
        "y": 2.069010016893664,
        "z": 7.424147296490934
      },
      "rotation": {
        "x": 0,
        "y": 270,
        "z": 0
      },
      "layer": "Procedural1"
    },
    {
      "assetId": "Wall_Decor_Photo_3",
      "id": "7|6",
      "kinematic": true,
      "position": {
        "x": 8.6988704854548,
        "y": 1.645465124765437,
        "z": 9.101192977733284
      },
      "rotation": {
        "x": 0,
        "y": 90,
        "z": 0
      },
      "layer": "Procedural1"
    }
  ],
  "proceduralParameters": {
    "ceilingColor": {
      "b": 0.34901960784313724,
      "g": 0.42745098039215684,
      "r": 0.37254901960784315
    },
    "ceilingMaterial": "PureWhite",
    "floorColliderThickness": 1.0,
    "lights": [
      {
        "id": "DirectionalLight",
        "indirectMultiplier": 1.0,
        "intensity": 1,
        "position": {
          "x": 0.84,
          "y": 0.1855,
          "z": -1.09
        },
        "rgb": {
          "r": 1.0,
          "g": 1.0,
          "b": 1.0
        },
        "rotation": {
          "x": 66,
          "y": 75,
          "z": 0
        },
        "shadow": {
          "type": "Soft",
          "strength": 1,
          "normalBias": 0,
          "bias": 0,
          "nearPlane": 0.2,
          "resolution": "FromQualitySettings"
        },
        "type": "directional"
      },
      {
        "id": "light_4",
        "intensity": 0.45,
        "position": {
          "x": 9.7625,
          "y": 2.7859275340171394,
          "z": 3.2539999999999996
        },
        "range": 15,
        "rgb": {
          "r": 1.0,
          "g": 0.855,
          "b": 0.722
        },
        "shadow": {
          "type": "Soft",
          "strength": 1,
          "normalBias": 0,
          "bias": 0.05,
          "nearPlane": 0.2,
          "resolution": "FromQualitySettings"
        },
        "type": "point",
        "layer": "Procedural3",
        "cullingMaskOff": [
          "Procedural0",
          "Procedural1",
          "Procedural2"
        ]
      },
      {
        "id": "light_5",
        "intensity": 0.45,
        "position": {
          "x": 4.121840001843828,
          "y": 2.7859275340171394,
          "z": 4.121840001843828
        },
        "range": 15,
        "rgb": {
          "r": 1.0,
          "g": 0.855,
          "b": 0.722
        },
        "shadow": {
          "type": "Soft",
          "strength": 1,
          "normalBias": 0,
          "bias": 0.05,
          "nearPlane": 0.2,
          "resolution": "FromQualitySettings"
        },
        "type": "point",
        "layer": "Procedural1",
        "cullingMaskOff": [
          "Procedural0",
          "Procedural2",
          "Procedural3"
        ]
      },
      {
        "id": "light_6",
        "intensity": 0.45,
        "position": {
          "x": 4.339,
          "y": 2.7859275340171394,
          "z": 9.762500000000001
        },
        "range": 15,
        "rgb": {
          "r": 1.0,
          "g": 0.855,
          "b": 0.722
        },
        "shadow": {
          "type": "Soft",
          "strength": 1,
          "normalBias": 0,
          "bias": 0.05,
          "nearPlane": 0.2,
          "resolution": "FromQualitySettings"
        },
        "type": "point",
        "layer": "Procedural2",
        "cullingMaskOff": [
          "Procedural0",
          "Procedural1",
          "Procedural3"
        ]
      },
      {
        "id": "light_7",
        "intensity": 0.45,
        "position": {
          "x": 10.847500000000002,
          "y": 2.7859275340171394,
          "z": 9.7625
        },
        "range": 15,
        "rgb": {
          "r": 1.0,
          "g": 0.855,
          "b": 0.722
        },
        "shadow": {
          "type": "Soft",
          "strength": 1,
          "normalBias": 0,
          "bias": 0.05,
          "nearPlane": 0.2,
          "resolution": "FromQualitySettings"
        },
        "type": "point",
        "layer": "Procedural1",
        "cullingMaskOff": [
          "Procedural0",
          "Procedural2",
          "Procedural3"
        ]
      }
    ],
    "receptacleHeight": 0.7,
    "reflections": [],
    "skyboxId": "SkyAlbanyHill"
  },
  "rooms": [
    {
      "ceilings": [],
      "children": [],
      "floorMaterial": "WoodFineDarkFloorsRedNRM1",
      "floorPolygon": [
        {
          "x": 6.508,
          "y": 0,
          "z": 0.0
        },
        {
          "x": 6.508,
          "y": 0,
          "z": 6.508
        },
        {
          "x": 8.678,
          "y": 0,
          "z": 6.508
        },
        {
          "x": 13.017,
          "y": 0,
          "z": 6.508
        },
        {
          "x": 13.017,
          "y": 0,
          "z": 0.0
        }
      ],
      "id": "room|4",
      "roomType": "Bedroom",
      "layer": "Procedural3"
    },
    {
      "ceilings": [],
      "children": [],
      "floorMaterial": "Wood 1",
      "floorPolygon": [
        {
          "x": 4.339,
          "y": 0,
          "z": 0.0
        },
        {
          "x": 4.339,
          "y": 0,
          "z": 4.339
        },
        {
          "x": 0.0,
          "y": 0,
          "z": 4.339
        },
        {
          "x": 0.0,
          "y": 0,
          "z": 6.508
        },
        {
          "x": 6.508,
          "y": 0,
          "z": 6.508
        },
        {
          "x": 6.508,
          "y": 0,
          "z": 0.0
        }
      ],
      "id": "room|5",
      "roomType": "Bathroom",
      "layer": "Procedural1"
    },
    {
      "ceilings": [],
      "children": [],
      "floorMaterial": "TexturesCom_WoodFine0038_1_seamless_S",
      "floorPolygon": [
        {
          "x": 0.0,
          "y": 0,
          "z": 13.017
        },
        {
          "x": 8.678,
          "y": 0,
          "z": 13.017
        },
        {
          "x": 8.678,
          "y": 0,
          "z": 6.508
        },
        {
          "x": 6.508,
          "y": 0,
          "z": 6.508
        },
        {
          "x": 0.0,
          "y": 0,
          "z": 6.508
        }
      ],
      "id": "room|6",
      "roomType": "Kitchen",
      "layer": "Procedural2"
    },
    {
      "ceilings": [],
      "children": [],
      "floorMaterial": "LightWoodCounters3",
      "floorPolygon": [
        {
          "x": 8.678,
          "y": 0,
          "z": 6.508
        },
        {
          "x": 8.678,
          "y": 0,
          "z": 13.017
        },
        {
          "x": 13.017,
          "y": 0,
          "z": 13.017
        },
        {
          "x": 13.017,
          "y": 0,
          "z": 6.508
        }
      ],
      "id": "room|7",
      "roomType": "LivingRoom",
      "layer": "Procedural1"
    }
  ],
  "walls": [
    {
      "color": {
        "b": 0.34901960784313724,
        "g": 0.42745098039215684,
        "r": 0.37254901960784315
      },
      "id": "wall|4|6.51|0.00|6.51|6.51",
      "material": "PureWhite",
      "polygon": [
        {
          "x": 6.508,
          "y": 0,
          "z": 0.0
        },
        {
          "x": 6.508,
          "y": 0,
          "z": 6.508
        },
        {
          "x": 6.508,
          "y": 2.9859275340171396,
          "z": 0.0
        },
        {
          "x": 6.508,
          "y": 2.9859275340171396,
          "z": 6.508
        }
      ],
      "roomId": "room|4",
      "layer": "Procedural3"
    },
    {
      "color": {
        "b": 0.34901960784313724,
        "g": 0.42745098039215684,
        "r": 0.37254901960784315
      },
      "id": "wall|4|6.51|6.51|8.68|6.51",
      "material": "PureWhite",
      "polygon": [
        {
          "x": 6.508,
          "y": 0,
          "z": 6.508
        },
        {
          "x": 8.678,
          "y": 0,
          "z": 6.508
        },
        {
          "x": 6.508,
          "y": 2.9859275340171396,
          "z": 6.508
        },
        {
          "x": 8.678,
          "y": 2.9859275340171396,
          "z": 6.508
        }
      ],
      "roomId": "room|4",
      "layer": "Procedural3"
    },
    {
      "color": {
        "b": 0.34901960784313724,
        "g": 0.42745098039215684,
        "r": 0.37254901960784315
      },
      "id": "wall|4|8.68|6.51|13.02|6.51",
      "material": "PureWhite",
      "polygon": [
        {
          "x": 8.678,
          "y": 0,
          "z": 6.508
        },
        {
          "x": 13.017,
          "y": 0,
          "z": 6.508
        },
        {
          "x": 8.678,
          "y": 2.9859275340171396,
          "z": 6.508
        },
        {
          "x": 13.017,
          "y": 2.9859275340171396,
          "z": 6.508
        }
      ],
      "roomId": "room|4",
      "layer": "Procedural3"
    },
    {
      "color": {
        "b": 0.34901960784313724,
        "g": 0.42745098039215684,
        "r": 0.37254901960784315
      },
      "id": "wall|4|13.02|0.00|13.02|6.51",
      "material": "PureWhite",
      "polygon": [
        {
          "x": 13.017,
          "y": 0,
          "z": 6.508
        },
        {
          "x": 13.017,
          "y": 0,
          "z": 0.0
        },
        {
          "x": 13.017,
          "y": 2.9859275340171396,
          "z": 6.508
        },
        {
          "x": 13.017,
          "y": 2.9859275340171396,
          "z": 0.0
        }
      ],
      "roomId": "room|4",
      "layer": "Procedural3"
    },
    {
      "color": {
        "b": 0.34901960784313724,
        "g": 0.42745098039215684,
        "r": 0.37254901960784315
      },
      "id": "wall|4|6.51|0.00|13.02|0.00",
      "material": "PureWhite",
      "polygon": [
        {
          "x": 13.017,
          "y": 0,
          "z": 0.0
        },
        {
          "x": 6.508,
          "y": 0,
          "z": 0.0
        },
        {
          "x": 13.017,
          "y": 2.9859275340171396,
          "z": 0.0
        },
        {
          "x": 6.508,
          "y": 2.9859275340171396,
          "z": 0.0
        }
      ],
      "roomId": "room|4",
      "layer": "Procedural3"
    },
    {
      "color": {
        "b": 0.34901960784313724,
        "g": 0.42745098039215684,
        "r": 0.37254901960784315
      },
      "id": "wall|5|4.34|0.00|4.34|4.34",
      "material": "PureWhite",
      "polygon": [
        {
          "x": 4.339,
          "y": 0,
          "z": 0.0
        },
        {
          "x": 4.339,
          "y": 0,
          "z": 4.339
        },
        {
          "x": 4.339,
          "y": 2.9859275340171396,
          "z": 0.0
        },
        {
          "x": 4.339,
          "y": 2.9859275340171396,
          "z": 4.339
        }
      ],
      "roomId": "room|5",
      "layer": "Procedural1"
    },
    {
      "color": {
        "b": 0.34901960784313724,
        "g": 0.42745098039215684,
        "r": 0.37254901960784315
      },
      "id": "wall|5|0.00|4.34|4.34|4.34",
      "material": "PureWhite",
      "polygon": [
        {
          "x": 4.339,
          "y": 0,
          "z": 4.339
        },
        {
          "x": 0.0,
          "y": 0,
          "z": 4.339
        },
        {
          "x": 4.339,
          "y": 2.9859275340171396,
          "z": 4.339
        },
        {
          "x": 0.0,
          "y": 2.9859275340171396,
          "z": 4.339
        }
      ],
      "roomId": "room|5",
      "layer": "Procedural1"
    },
    {
      "color": {
        "b": 0.34901960784313724,
        "g": 0.42745098039215684,
        "r": 0.37254901960784315
      },
      "id": "wall|5|0.00|4.34|0.00|6.51",
      "material": "PureWhite",
      "polygon": [
        {
          "x": 0.0,
          "y": 0,
          "z": 4.339
        },
        {
          "x": 0.0,
          "y": 0,
          "z": 6.508
        },
        {
          "x": 0.0,
          "y": 2.9859275340171396,
          "z": 4.339
        },
        {
          "x": 0.0,
          "y": 2.9859275340171396,
          "z": 6.508
        }
      ],
      "roomId": "room|5",
      "layer": "Procedural1"
    },
    {
      "color": {
        "b": 0.34901960784313724,
        "g": 0.42745098039215684,
        "r": 0.37254901960784315
      },
      "id": "wall|5|0.00|6.51|6.51|6.51",
      "material": "PureWhite",
      "polygon": [
        {
          "x": 0.0,
          "y": 0,
          "z": 6.508
        },
        {
          "x": 6.508,
          "y": 0,
          "z": 6.508
        },
        {
          "x": 0.0,
          "y": 2.9859275340171396,
          "z": 6.508
        },
        {
          "x": 6.508,
          "y": 2.9859275340171396,
          "z": 6.508
        }
      ],
      "roomId": "room|5",
      "layer": "Procedural1"
    },
    {
      "color": {
        "b": 0.34901960784313724,
        "g": 0.42745098039215684,
        "r": 0.37254901960784315
      },
      "id": "wall|5|6.51|0.00|6.51|6.51",
      "material": "PureWhite",
      "polygon": [
        {
          "x": 6.508,
          "y": 0,
          "z": 6.508
        },
        {
          "x": 6.508,
          "y": 0,
          "z": 0.0
        },
        {
          "x": 6.508,
          "y": 2.9859275340171396,
          "z": 6.508
        },
        {
          "x": 6.508,
          "y": 2.9859275340171396,
          "z": 0.0
        }
      ],
      "roomId": "room|5",
      "layer": "Procedural1"
    },
    {
      "color": {
        "b": 0.34901960784313724,
        "g": 0.42745098039215684,
        "r": 0.37254901960784315
      },
      "id": "wall|5|4.34|0.00|6.51|0.00",
      "material": "PureWhite",
      "polygon": [
        {
          "x": 6.508,
          "y": 0,
          "z": 0.0
        },
        {
          "x": 4.339,
          "y": 0,
          "z": 0.0
        },
        {
          "x": 6.508,
          "y": 2.9859275340171396,
          "z": 0.0
        },
        {
          "x": 4.339,
          "y": 2.9859275340171396,
          "z": 0.0
        }
      ],
      "roomId": "room|5",
      "layer": "Procedural1"
    },
    {
      "color": {
        "b": 0.34901960784313724,
        "g": 0.42745098039215684,
        "r": 0.37254901960784315
      },
      "id": "wall|6|0.00|13.02|8.68|13.02",
      "material": "PureWhite",
      "polygon": [
        {
          "x": 0.0,
          "y": 0,
          "z": 13.017
        },
        {
          "x": 8.678,
          "y": 0,
          "z": 13.017
        },
        {
          "x": 0.0,
          "y": 2.9859275340171396,
          "z": 13.017
        },
        {
          "x": 8.678,
          "y": 2.9859275340171396,
          "z": 13.017
        }
      ],
      "roomId": "room|6",
      "layer": "Procedural2"
    },
    {
      "color": {
        "b": 0.34901960784313724,
        "g": 0.42745098039215684,
        "r": 0.37254901960784315
      },
      "id": "wall|6|8.68|6.51|8.68|13.02",
      "material": "PureWhite",
      "polygon": [
        {
          "x": 8.678,
          "y": 0,
          "z": 13.017
        },
        {
          "x": 8.678,
          "y": 0,
          "z": 6.508
        },
        {
          "x": 8.678,
          "y": 2.9859275340171396,
          "z": 13.017
        },
        {
          "x": 8.678,
          "y": 2.9859275340171396,
          "z": 6.508
        }
      ],
      "roomId": "room|6",
      "layer": "Procedural2"
    },
    {
      "color": {
        "b": 0.34901960784313724,
        "g": 0.42745098039215684,
        "r": 0.37254901960784315
      },
      "id": "wall|6|6.51|6.51|8.68|6.51",
      "material": "PureWhite",
      "polygon": [
        {
          "x": 8.678,
          "y": 0,
          "z": 6.508
        },
        {
          "x": 6.508,
          "y": 0,
          "z": 6.508
        },
        {
          "x": 8.678,
          "y": 2.9859275340171396,
          "z": 6.508
        },
        {
          "x": 6.508,
          "y": 2.9859275340171396,
          "z": 6.508
        }
      ],
      "roomId": "room|6",
      "layer": "Procedural2"
    },
    {
      "color": {
        "b": 0.34901960784313724,
        "g": 0.42745098039215684,
        "r": 0.37254901960784315
      },
      "id": "wall|6|0.00|6.51|6.51|6.51",
      "material": "PureWhite",
      "polygon": [
        {
          "x": 6.508,
          "y": 0,
          "z": 6.508
        },
        {
          "x": 0.0,
          "y": 0,
          "z": 6.508
        },
        {
          "x": 6.508,
          "y": 2.9859275340171396,
          "z": 6.508
        },
        {
          "x": 0.0,
          "y": 2.9859275340171396,
          "z": 6.508
        }
      ],
      "roomId": "room|6",
      "layer": "Procedural2"
    },
    {
      "color": {
        "b": 0.34901960784313724,
        "g": 0.42745098039215684,
        "r": 0.37254901960784315
      },
      "id": "wall|6|0.00|6.51|0.00|13.02",
      "material": "PureWhite",
      "polygon": [
        {
          "x": 0.0,
          "y": 0,
          "z": 6.508
        },
        {
          "x": 0.0,
          "y": 0,
          "z": 13.017
        },
        {
          "x": 0.0,
          "y": 2.9859275340171396,
          "z": 6.508
        },
        {
          "x": 0.0,
          "y": 2.9859275340171396,
          "z": 13.017
        }
      ],
      "roomId": "room|6",
      "layer": "Procedural2"
    },
    {
      "color": {
        "b": 0.34901960784313724,
        "g": 0.42745098039215684,
        "r": 0.37254901960784315
      },
      "id": "wall|7|8.68|6.51|8.68|13.02",
      "material": "PureWhite",
      "polygon": [
        {
          "x": 8.678,
          "y": 0,
          "z": 6.508
        },
        {
          "x": 8.678,
          "y": 0,
          "z": 13.017
        },
        {
          "x": 8.678,
          "y": 2.9859275340171396,
          "z": 6.508
        },
        {
          "x": 8.678,
          "y": 2.9859275340171396,
          "z": 13.017
        }
      ],
      "roomId": "room|7",
      "layer": "Procedural1"
    },
    {
      "color": {
        "b": 0.34901960784313724,
        "g": 0.42745098039215684,
        "r": 0.37254901960784315
      },
      "id": "wall|7|8.68|13.02|13.02|13.02",
      "material": "PureWhite",
      "polygon": [
        {
          "x": 8.678,
          "y": 0,
          "z": 13.017
        },
        {
          "x": 13.017,
          "y": 0,
          "z": 13.017
        },
        {
          "x": 8.678,
          "y": 2.9859275340171396,
          "z": 13.017
        },
        {
          "x": 13.017,
          "y": 2.9859275340171396,
          "z": 13.017
        }
      ],
      "roomId": "room|7",
      "layer": "Procedural1"
    },
    {
      "color": {
        "b": 0.34901960784313724,
        "g": 0.42745098039215684,
        "r": 0.37254901960784315
      },
      "id": "wall|7|13.02|6.51|13.02|13.02",
      "material": "PureWhite",
      "polygon": [
        {
          "x": 13.017,
          "y": 0,
          "z": 13.017
        },
        {
          "x": 13.017,
          "y": 0,
          "z": 6.508
        },
        {
          "x": 13.017,
          "y": 2.9859275340171396,
          "z": 13.017
        },
        {
          "x": 13.017,
          "y": 2.9859275340171396,
          "z": 6.508
        }
      ],
      "roomId": "room|7",
      "layer": "Procedural1"
    },
    {
      "color": {
        "b": 0.34901960784313724,
        "g": 0.42745098039215684,
        "r": 0.37254901960784315
      },
      "id": "wall|7|8.68|6.51|13.02|6.51",
      "material": "PureWhite",
      "polygon": [
        {
          "x": 13.017,
          "y": 0,
          "z": 6.508
        },
        {
          "x": 8.678,
          "y": 0,
          "z": 6.508
        },
        {
          "x": 13.017,
          "y": 2.9859275340171396,
          "z": 6.508
        },
        {
          "x": 8.678,
          "y": 2.9859275340171396,
          "z": 6.508
        }
      ],
      "roomId": "room|7",
      "layer": "Procedural1"
    },
    {
      "id": "wall|exterior|4.34|0.00|4.34|4.34",
      "material": "FireplaceTiles2",
      "polygon": [
        {
          "x": 4.339,
          "y": 2.9859275340171396,
          "z": 4.339
        },
        {
          "x": 4.339,
          "y": 2.9859275340171396,
          "z": 0.0
        },
        {
          "x": 4.339,
          "y": 0,
          "z": 4.339
        },
        {
          "x": 4.339,
          "y": 0,
          "z": 0.0
        }
      ],
      "roomId": "room|5",
      "layer": "Procedural1"
    },
    {
      "id": "wall|exterior|0.00|4.34|0.00|6.51",
      "material": "FireplaceTiles2",
      "polygon": [
        {
          "x": 0.0,
          "y": 2.9859275340171396,
          "z": 6.508
        },
        {
          "x": 0.0,
          "y": 2.9859275340171396,
          "z": 4.339
        },
        {
          "x": 0.0,
          "y": 0,
          "z": 6.508
        },
        {
          "x": 0.0,
          "y": 0,
          "z": 4.339
        }
      ],
      "roomId": "room|5",
      "layer": "Procedural1"
    },
    {
      "id": "wall|exterior|0.00|4.34|4.34|4.34",
      "material": "FireplaceTiles2",
      "polygon": [
        {
          "x": 0.0,
          "y": 2.9859275340171396,
          "z": 4.339
        },
        {
          "x": 4.339,
          "y": 2.9859275340171396,
          "z": 4.339
        },
        {
          "x": 0.0,
          "y": 0,
          "z": 4.339
        },
        {
          "x": 4.339,
          "y": 0,
          "z": 4.339
        }
      ],
      "roomId": "room|5",
      "layer": "Procedural1"
    },
    {
      "id": "wall|exterior|4.34|0.00|6.51|0.00",
      "material": "FireplaceTiles2",
      "polygon": [
        {
          "x": 4.339,
          "y": 2.9859275340171396,
          "z": 0.0
        },
        {
          "x": 6.508,
          "y": 2.9859275340171396,
          "z": 0.0
        },
        {
          "x": 4.339,
          "y": 0,
          "z": 0.0
        },
        {
          "x": 6.508,
          "y": 0,
          "z": 0.0
        }
      ],
      "roomId": "room|5",
      "layer": "Procedural1"
    },
    {
      "id": "wall|exterior|0.00|13.02|8.68|13.02",
      "material": "FireplaceTiles2",
      "polygon": [
        {
          "x": 8.678,
          "y": 2.9859275340171396,
          "z": 13.017
        },
        {
          "x": 0.0,
          "y": 2.9859275340171396,
          "z": 13.017
        },
        {
          "x": 8.678,
          "y": 0,
          "z": 13.017
        },
        {
          "x": 0.0,
          "y": 0,
          "z": 13.017
        }
      ],
      "roomId": "room|6",
      "layer": "Procedural2"
    },
    {
      "id": "wall|exterior|0.00|6.51|0.00|13.02",
      "material": "FireplaceTiles2",
      "polygon": [
        {
          "x": 0.0,
          "y": 2.9859275340171396,
          "z": 13.017
        },
        {
          "x": 0.0,
          "y": 2.9859275340171396,
          "z": 6.508
        },
        {
          "x": 0.0,
          "y": 0,
          "z": 13.017
        },
        {
          "x": 0.0,
          "y": 0,
          "z": 6.508
        }
      ],
      "roomId": "room|6",
      "layer": "Procedural2"
    },
    {
      "id": "wall|exterior|6.51|0.00|13.02|0.00",
      "material": "FireplaceTiles2",
      "polygon": [
        {
          "x": 6.508,
          "y": 2.9859275340171396,
          "z": 0.0
        },
        {
          "x": 13.017,
          "y": 2.9859275340171396,
          "z": 0.0
        },
        {
          "x": 6.508,
          "y": 0,
          "z": 0.0
        },
        {
          "x": 13.017,
          "y": 0,
          "z": 0.0
        }
      ],
      "roomId": "room|4",
      "layer": "Procedural3"
    },
    {
      "id": "wall|exterior|13.02|0.00|13.02|6.51",
      "material": "FireplaceTiles2",
      "polygon": [
        {
          "x": 13.017,
          "y": 2.9859275340171396,
          "z": 0.0
        },
        {
          "x": 13.017,
          "y": 2.9859275340171396,
          "z": 6.508
        },
        {
          "x": 13.017,
          "y": 0,
          "z": 0.0
        },
        {
          "x": 13.017,
          "y": 0,
          "z": 6.508
        }
      ],
      "roomId": "room|4",
      "layer": "Procedural3"
    },
    {
      "id": "wall|exterior|8.68|13.02|13.02|13.02",
      "material": "FireplaceTiles2",
      "polygon": [
        {
          "x": 13.017,
          "y": 2.9859275340171396,
          "z": 13.017
        },
        {
          "x": 8.678,
          "y": 2.9859275340171396,
          "z": 13.017
        },
        {
          "x": 13.017,
          "y": 0,
          "z": 13.017
        },
        {
          "x": 8.678,
          "y": 0,
          "z": 13.017
        }
      ],
      "roomId": "room|7",
      "layer": "Procedural1"
    },
    {
      "id": "wall|exterior|13.02|6.51|13.02|13.02",
      "material": "FireplaceTiles2",
      "polygon": [
        {
          "x": 13.017,
          "y": 2.9859275340171396,
          "z": 6.508
        },
        {
          "x": 13.017,
          "y": 2.9859275340171396,
          "z": 13.017
        },
        {
          "x": 13.017,
          "y": 0,
          "z": 6.508
        },
        {
          "x": 13.017,
          "y": 0,
          "z": 13.017
        }
      ],
      "roomId": "room|7",
      "layer": "Procedural1"
    }
  ],
  "windows": [
    {
      "assetId": "Window_Slider_48x36",
      "assetOffset": {
        "x": -0.0020703375339508057,
        "y": -0.002639956772327423,
        "z": 0.03877231478691101
      },
      "boundingBox": {
        "max": {
          "x": 7.857243005223611,
          "y": 1.9474288060829907,
          "z": 0
        },
        "min": {
          "x": 6.643252197690347,
          "y": 1.0357638358638555,
          "z": 0
        }
      },
      "id": "window|6|0",
      "room0": "room|6",
      "room1": "room|6",
      "wall0": "wall|6|0.00|13.02|8.68|13.02",
      "wall1": "wall|exterior|0.00|13.02|8.68|13.02"
    },
    {
      "assetId": "Window_Slider_36x36",
      "assetOffset": {
        "x": -0.0018267780542373657,
        "y": -0.0007938370108604431,
        "z": 0.03973130136728287
      },
      "boundingBox": {
        "max": {
          "x": 1.013444050017993,
          "y": 1.946060298340109,
          "z": 0
        },
        "min": {
          "x": 0.10427342242399895,
          "y": 1.0347186088130742,
          "z": 0
        }
      },
      "id": "window|4|0",
      "room0": "room|4",
      "room1": "room|4",
      "wall0": "wall|4|13.02|0.00|13.02|6.51",
      "wall1": "wall|exterior|13.02|0.00|13.02|6.51"
    },
    {
      "assetId": "Window_Hung_48x32",
      "assetOffset": {
        "x": -0.02731071412563324,
        "y": -0.0,
        "z": 0.039758820086717606
      },
      "boundingBox": {
        "max": {
          "x": 4.696279588155887,
          "y": 1.9229179977939397,
          "z": 0
        },
        "min": {
          "x": 3.480908337049625,
          "y": 1.05670831199148,
          "z": 0
        }
      },
      "id": "window|4|1",
      "room0": "room|4",
      "room1": "room|4",
      "wall0": "wall|4|6.51|0.00|13.02|0.00",
      "wall1": "wall|exterior|6.51|0.00|13.02|0.00"
    },
    {
      "assetId": "Window_Slider_36x36",
      "assetOffset": {
        "x": -0.0018267780542373657,
        "y": -0.0007938370108604431,
        "z": 0.03973130136728287
      },
      "boundingBox": {
        "max": {
          "x": 4.891870244816888,
          "y": 1.946060298340109,
          "z": 0
        },
        "min": {
          "x": 3.9826996172228935,
          "y": 1.0347186088130742,
          "z": 0
        }
      },
      "id": "window|7|0",
      "room0": "room|7",
      "room1": "room|7",
      "wall0": "wall|7|13.02|6.51|13.02|13.02",
      "wall1": "wall|exterior|13.02|6.51|13.02|13.02"
    },
    {
      "assetId": "Window_Hung_36x32",
      "assetOffset": {
        "x": -0.02685144916176796,
        "y": -0.000718533992767334,
        "z": 0.0400175042450428
      },
      "boundingBox": {
        "max": {
          "x": 3.153833721697772,
          "y": 1.9457410037086278,
          "z": 0
        },
        "min": {
          "x": 2.2419957266454342,
          "y": 1.036295896725443,
          "z": 0
        }
      },
      "id": "window|7|1",
      "room0": "room|7",
      "room1": "room|7",
      "wall0": "wall|7|8.68|13.02|13.02|13.02",
      "wall1": "wall|exterior|8.68|13.02|13.02|13.02"
    }
  ]
}